{
  "adana": ["seyhan","yüreğir","çukurova","sarıçam","ceyhan","kozan","imamoğlu","karaisalı","pozantı","tufanbeyli","feke","aladağ","saimbeyli","karataş","yumurtalık"],
  "adıyaman": ["merkez","besni","kahta","gölbaşı","tut","sincik","gerger","çelikhan","samsat"],
  "afyonkarahisar": ["merkez","dinar","bolvadin","sandıklı","emirdağ","sincanlı","şuhut","çay","iscehisar","ihsaniye","başmakçı","çobanlar","bayat","sultandağı","dazkırı","hocalar","kızılören","evciler","hocalar"],
  "ağrı": ["merkez","doğubayazıt","patnos","diyadin","eleşkirt","hamur","taşlıçay","tutak"],
  "aksaray": ["merkez","ortaköy","eskil","güzelyurt","ağaçören","gülağaç","sarıyahşi","sultanhanı"],
  "amasya": ["merkez","suluova","merzifon","taşova","gümüşhacıköy","göynücek","hamamözü"],
  "ankara": ["altındağ","çankaya","etimesgut","gölbaşı","keçiören","mamak","pursaklar","sincan","yenimahalle","polatlı","kızılcahamam","beypazarı","nallıhan","ayaş","bala","çubuk","elmadağ","güdül","haymana","kalecik","kahramankazan","akyurt","evren","çamlıdere","şereflikoçhisar"],
  "antalya": ["muratpaşa","konyaaltı","kepez","aksu","döşemealtı","alanya","manavgat","serik","kemer","kumluca","kaş","finike","elmalı","korkuteli","gazipaşa","akseki","demre","gündoğmuş","ibradı"],
  "ardahan": ["merkez","çıldır","damal","göle","hanak","posof"],
  "artvin": ["merkez","ardanuç","arhavi","borçka","hopa","murgul","şavşat","yusufeli","kemalpaşa"],
  "aydın": ["efeler","söke","didim","nazilli","kuşadası","çine","incirliova","germencik","bozdoğan","karacasu","kuyucak","sultanhisar","yenipazar","köşk","buharkent","karpuzlu"],
  "balıkesir": ["altıeylül","karesi","bandırma","ayvalık","edremit","gönen","susurluk","bigadiç","burhaniye","dursunbey","erdek","havran","ivrindi","kepsut","manyas","marmara","savaştepe","sındırgı","gömeç","balya"],
  "bartın": ["merkez","amasra","kurucaşile","ulus"],
  "batman": ["merkez","beşiri","gercüş","hasankeyf","kozluk","sason"],
  "bayburt": ["merkez","aydıntepe","demirözü"],
  "bilecik": ["merkez","bozüyük","osmaneli","söğüt","gölpazarı","yenipazar","pazaryeri","inhisar"],
  "bingöl": ["merkez","genç","karlıova","solhan","adaklı","kiğı","yayladere","yedisu"],
  "bitlis": ["merkez","ahlat","tatvan","adilcevaz","güroymak","hizan","mutki"],
  "bolu": ["merkez","düzce","gerede","mudurnu","yeniçağa","göynük","mengen","dörtdivan","seben","kıbrıscık"],
  "burdur": ["merkez","bucak","gölhisar","yeşilova","tefenni","ağlasun","altınyayla","çavdır","karamanlı","kemer","çeltikçi"],
  "bursa": ["osmangazi","nilüfer","yıldırım","gürsu","kestel","mudanya","gemlik","inegöl","iznik","karacabey","orhangazi","yenişehir","mustafakemalpaşa","orhaneli","harmancık","keles","büyükorhan"],
  "çanakkale": ["merkez","gelibolu","biga","çan","ezine","ayvacık","bayramiç","yenice","eceabat","lapseki","bozcaada","gökçeada"],
  "çankırı": ["merkez","çerkeş","ilgaz","kurşunlu","eldivan","yapraklı","atkaracalar","kızılırmak","korgun","orta","şabanözü","bayramören"],
  "çorum": ["merkez","sungurlu","osmancık","iskilip","alaca","bayat","mecitözü","kargı","ortaköy","uğurludağ","boğazkale","dodurga","laçin","oğuzlar"],
  "denizli": ["pamukkale","merkezefendi","acıpayam","tavas","çivril","buldan","honaz","sarayköy","bekilli","babadağ","beyağaç","güney","baklan","çameli","çal","kale","serinhisar","bozkurt"],
  "diyarbakır": ["bağlar","kayapınar","sur","yenişehir","bismil","çınar","çermik","çüngüş","dicle","eğil","ergani","hani","hazro","kocaköy","kulp","lice","silvan","hazro"],
  "düzce": ["merkez","akçakoca","kaynaşlı","gölyaka","çilimli","yığılca","cumayeri","gümüşova"],
  "edirne": ["merkez","keşan","uzunköprü","ipsala","havsa","enez","meriç","süloğlu","lalapaşa"],
  "elazığ": ["merkez","kovancılar","karakoçan","palu","maden","arıcak","alacakaya","sivrice","baskil","ağın","keban"],
  "erzincan": ["merkez","tercan","refahiye","kemah","üzümlü","çayırlı","ilıç","kemaliye","otlukbeli"],
  "erzurum": ["yakutiye","aziziye","palandöken","horasan","pasinler","tortum","oltu","uzundere","şenkaya","narman","olur","ispir","tekman","aşkale","çat","hınıs","karaçoban","karayazı","köprüköy","pazaryolu"],
  "eskişehir": ["odunpazarı","tepebaşı","sivrihisar","çifteler","mahmudiye","mihalıççık","seyitgazi","alpu","beylikova","günyüzü","han","inönü","mihalgazi","sarıcakaya"],
  "gaziantep": ["şahinbey","şehitkamil","nizip","islahiye","nurdağı","oğuzeli","yavuzeli","araban","karkamış"],
  "giresun": ["merkez","bulancak","espiye","tirebolu","görele","eynesil","keşap","piraziz","yağlıdere","dereli","doğankent","çamoluk","alucra","çanakçı","güce","şebinkarahisar"],
  "gümüşhane": ["merkez","kelkit","şiran","kürtün","köse","torul"],
  "hakkari": ["merkez","çukurca","yüksekova","şemdinli"],
  "hatay": ["antakya","defne","arsuz","payas","iskenderun","dörtyol","belen","erzin","altınözü","hassa","kırıkhan","kumlu","reyhanlı","samandağ","yayladağı"],
  "ığdır": ["merkez","aralık","karakoyunlu","tuzluca"],
  "isparta": ["merkez","eğirdir","yalvaç","şarkikaraağaç","gelendost","sütçüler","senirkent","uluborlu","keçiborlu","aksu","yenişarbademli","gönen","atabey"],
  "istanbul": ["adalar","arnavutköy","ataşehir","avcılar","bağcılar","bahçelievler","bakırköy","başakşehir","bayrampaşa","beşiktaş","beykoz","beylikdüzü","beyoğlu","büyükçekmece","çatalca","çekmeköy","esenler","esenyurt","eyüpsultan","fatih","gaziosmanpaşa","güngören","kadıköy","kağıthane","kartal","küçükçekmece","maltepe","pendik","sancaktepe","sarıyer","silivri","sultanbeyli","sultangazi","şile","şişli","tuzla","ümraniye","üsküdar","zeytinburnu"],
  "izmir": ["konak","karşıyaka","bornova","buca","çiğli","balçova","narlıdere","güzelbahçe","gaziemir","karabağlar","bayraklı","aliağa","bergama","dikili","foça","kemalpaşa","menemen","menderes","seferihisar","selçuk","torbalı","urla","kiraz","ödemiş","tire","bayındır","beydağ","karaburun","çeşme","kınık"],
  "kahramanmaraş": ["onikişubat","dulkadiroğlu","afşin","elbistan","göksun","pazarcık","türkoğlu","andırın","çağlayancerit","ekinözü","nurhak"],
  "karabük": ["merkez","safranbolu","yenice","eskipazar","eflani","ovacık"],
  "karaman": ["merkez","ermenek","ayrancı","başyayla","kazımkarabekir","sarıveliler"],
  "kars": ["merkez","sarıkamış","kağızman","digor","arpaçay","akyaka","selim","susuz"],
  "kastamonu": ["merkez","taşköprü","tosya","inebolu","devrekani","cide","daday","araç","küre","ihsangazi","azdavay","bozkurt","çatalzeytin","doğanyurt","hanönü","pınarbaşı","seydiler","şenpazar","abana","ağlı"],
  "kayseri": ["melikgazi","kocasinan","talas","develi","yahyalı","yeşilhisar","incesu","bünyan","pınarbaşı","sarıoğlan","sarız","tomarza","akkışla","felahiye","hacılar","özvatan"],
  "kırıkkale": ["merkez","keskin","delice","sulakyurt","yahşihan","balışeyh","bahşili","çelebi","karakeçili"],
  "kırklareli": ["merkez","lüleburgaz","babaeski","vize","pınarhisar","pehlivanköy","demirköy","kofçaz"],
  "kırşehir": ["merkez","kaman","mucur","çiçekdağı","akpınar","akçakent","boztepe"],
  "kilis": ["merkez","elbeyli","musabeyli","polateli"],
  "kocaeli": ["izmit","körfez","derince","kartepe","başiskele","gölcük","çayırova","darıca","dilovası","gebze","karamürsel","kandıra"],
  "konya": ["selçuklu","meram","karatay","akşehir","beyşehir","bozkır","çumra","ereğli","ilgın","kadınhanı","karapınar","seydişehir","cihanbeyli","kulu","yunak","hadim","emirgazi","ahırlı","altınekin","çeltik","derbent","derebucak","doğanhisar","güneysınır","halkapınar","hüyük","sarayönü","taşkent","tuzlukçu","yalıhüyük"],
  "kütahya": ["merkez","simav","tavşanlı","gediz","emet","altıntaş","aslanapa","çavdarhisar","dumlupınar","domaniç","hisarcık","pazarlar","şaphane"],
  "malatya": ["battalgazi","yeşilyurt","doğanşehir","akçadağ","arapgir","arguvan","darende","doğanyol","hekimhan","kale","kuluncak","pütürge","yazıhan"],
  "manisa": ["şehzadeler","yunusemre","akhisar","alaşehir","demirci","gördes","kırkağaç","salihli","saruhanlı","selendi","soma","turgutlu","kula","ahmetli","gölmarmara","köprübaşı","sarıgöl"],
  "mardin": ["artuklu","kızıltepe","midyat","nusaybin","dargeçit","derik","mazıdağı","ömerli","savur","yeşilli"],
  "mersin": ["akdeniz","mezitli","toroslar","yenişehir","anamur","aydıncık","bozyazı","çamlıyayla","erdemli","gülnar","mut","silifke","tarsus"],
  "muğla": ["menteşe","bodrum","dalaman","datça","fethiye","kavaklıdere","köyceğiz","marmaris","milas","ortaca","seydikemer","ula","yatağan"],
  "muş": ["merkez","bulanık","malazgirt","varto","hasköy","korkut"],
  "nevşehir": ["merkez","ürgüp","avanos","gülşehir","hacıbektaş","derinkuyu","kozaklı","acıgöl"],
  "niğde": ["merkez","bor","çamardı","ulukışla","altunhisar","çiftlik"],
  "ordu": ["altınordu","ünye","fatsa","persembe","gülyalı","kumru","korgan","akkuş","gürgentepe","mesudiye","ulubey","çatalpınar","çamaş","ikizce","kabataş","gölköy","aybastı"],
  "osmaniye": ["merkez","kadirli","düziçi","bahçe","hasanbeyli","sumbas","toprakkale"],
  "rize": ["merkez","ardeşen","çayeli","fındıklı","kalkandere","pazar","güneysu","hemşin","ikizdere","iyidere","derepazarı","çamlıhemşin"],
  "sakarya": ["adapazarı","serdivan","erenler","arifiye","akyazı","hendek","karasu","kaynarca","sapanca","ferizli","geyve","karapürçek","pamukova","söğütlü","taraklı","kocaali"],
  "samsun": ["ilkadım","atakum","canik","tekkeköy","alaçam","bafra","çarşamba","havza","kavak","ladik","ondokuzmayıs","salıpazarı","terme","vezirköprü","yakakent","ayvacık","asarcık"],
  "siirt": ["merkez","baykan","eruh","kurtalan","pervari","şirvan","tillo"],
  "sinop": ["merkez","ayancık","boyabat","durağan","erfelek","gerze","türkeli","saraydüzü","dikmen"],
  "sivas": ["merkez","şarkışla","suşehri","zara","divriği","kangal","gemerek","gürün","yıldızeli","hafik","altınyayla","akıncılar","doğanşar","gölova","imranlı","koyulhisar","ulaş"],
  "şanlıurfa": ["haliliye","eyyübiye","karaköprü","siverek","viranşehir","suruç","akçakale","birecik","bozova","ceylanpınar","halfeti","harran","hilvan"],
  "şırnak": ["merkez","cizre","silopi","idil","uludere","beytüşşebap","güçlükonak"],
  "tekirdağ": ["süleymanpaşa","çorlu","çerkezköy","kapaklı","ergene","hayrabolu","malkara","marmaraereğlisi","muratlı","saray","şarköy"],
  "tokat": ["merkez","turhal","niksar","erbaa","zile","almus","artova","başçiftlik","pazar","reşadiye","sulusaray","yeşilyurt"],
  "trabzon": ["ortahisar","akçaabat","araklı","arsin","yomra","beşikdüzü","çarşıbaşı","çaykara","dernekpazarı","düzköy","hayrat","köprübaşı","maçka","of","sürmene","şalpazarı","tonya","vakfıkebir"],
  "tunceli": ["merkez","çemişgezek","hozat","mazgirt","nazımiye","ovacık","pertek","pülümür"],
  "uşak": ["merkez","banaz","eşme","karahallı","sivaslı","ulubey"],
  "van": ["ipekyolu","tuşba","edremit","erciş","muradiye","özalp","başkale","çaldıran","çatak","gevaş","gürpınar","saray","bahçesaray"],
  "yalova": ["merkez","altınova","armutlu","çınarcık","çiftlikköy","termal"],
  "yozgat": ["merkez","sorgun","boğazlıyan","akdağmadeni","yerköy","çandır","çayıralan","çekerek","kadışehri","saraykent","sarıkaya","şefaatli","aydıncık"],
  "zonguldak": ["merkez","karadeniz ereğli","çaycuma","devrek","kozlu","kilimli","gökçebey","alaplı","ereğli"]
}
